[
 {
  "table":"DD02L",
  "data":
  [
   {
    "TABNAME":"ZNWD_SO_HEADER",
    "AS4LOCAL":"L",
    "AS4VERS":0,
    "TABCLASS":"TRANSP",
    "SQLTAB":"",
    "DATMIN":0,
    "DATMAX":0,
    "DATAVG":0,
    "CLIDEP":"X",
    "BUFFERED":"",
    "COMPRFLAG":"",
    "LANGDEP":"",
    "ACTFLAG":"",
    "APPLCLASS":"",
    "AUTHCLASS":0,
    "AS4USER":"DEVELOPER",
    "AS4DATE":"0000-00-00",
    "AS4TIME":"00:00:00",
    "MASTERLANG":"E",
    "MAINFLAG":"X",
    "CONTFLAG":"A",
    "RESERVETAB":"",
    "GLOBALFLAG":"",
    "PROZPUFF":0,
    "VIEWCLASS":"",
    "VIEWGRANT":"",
    "MULTIPLEX":"",
    "SHLPEXI":"",
    "PROXYTYPE":"",
    "EXCLASS":1,
    "WRONGCL":"",
    "ALWAYSTRP":"",
    "ALLDATAINCL":"",
    "WITH_PARAMETERS":"",
    "EXVIEW_INCLUDED":"",
    "KEYMAX_FEATURE":"",
    "KEYLEN_FEATURE":"",
    "TABLEN_FEATURE":"",
    "NONTRP_INCLUDED":"",
    "VIEWREF":"",
    "VIEWREF_ERR":"",
    "VIEWREF_POS_CHG":"",
    "TBFUNC_INCLUDED":"",
    "IS_GTT":"",
    "SESSION_VAR_EX":"",
    "FROM_ENTITY":"",
    "PK_IS_INVHASH":"",
    "USED_SESSION_VARS":"",
    "ABAP_LANGUAGE_VERSION":"",
    "HDB_ONLY_ENTITY_INCLUDED":"",
    "FIELD_SUFFIX":"",
    "QUOTA_MAX_FIELDS":0,
    "QUOTA_MAX_BYTES":0,
    "QUOTA_SHARE_PARTNER":0,
    "QUOTA_SHARE_CUSTOMER":0
   }
  ]
 },
 {
  "table":"DD02T",
  "data":
  [
   {
    "TABNAME":"ZNWD_SO_HEADER",
    "DDLANGUAGE":"E",
    "AS4LOCAL":"N",
    "AS4VERS":0,
    "DDTEXT":"EPM: Sales Order Hader Table"
   }
  ]
 },
 {
  "table":"DD03L",
  "data":
  [
   {
    "TABNAME":"ZNWD_SO_HEADER",
    "FIELDNAME":"BILLINGSTATUS",
    "AS4LOCAL":"N",
    "AS4VERS":0,
    "POSITION":9,
    "KEYFLAG":"",
    "MANDATORY":"",
    "ROLLNAME":"SNWD_SO_CF_STATUS_CODE",
    "CHECKTABLE":"",
    "ADMINFIELD":"0",
    "INTTYPE":"C",
    "INTLEN":2,
    "REFTABLE":"",
    "PRECFIELD":"",
    "REFFIELD":"",
    "CONROUT":"",
    "NOTNULL":"",
    "DATATYPE":"CHAR",
    "LENG":1,
    "DECIMALS":0,
    "DOMNAME":"D_SO_CF",
    "SHLPORIGIN":"F",
    "TABLETYPE":"",
    "DEPTH":0,
    "COMPTYPE":"E",
    "REFTYPE":"",
    "LANGUFLAG":"",
    "DBPOSITION":0,
    "ANONYMOUS":"",
    "OUTPUTSTYLE":0,
    "SRS_ID":0
   },
   {
    "TABNAME":"ZNWD_SO_HEADER",
    "FIELDNAME":"BUSINESSPARTNER",
    "AS4LOCAL":"N",
    "AS4VERS":0,
    "POSITION":4,
    "KEYFLAG":"",
    "MANDATORY":"",
    "ROLLNAME":"SNWD_PARTNER_ID",
    "CHECKTABLE":"",
    "ADMINFIELD":"0",
    "INTTYPE":"C",
    "INTLEN":20,
    "REFTABLE":"",
    "PRECFIELD":"",
    "REFFIELD":"",
    "CONROUT":"",
    "NOTNULL":"",
    "DATATYPE":"CHAR",
    "LENG":10,
    "DECIMALS":0,
    "DOMNAME":"D_EPM_ID",
    "SHLPORIGIN":"D",
    "TABLETYPE":"",
    "DEPTH":0,
    "COMPTYPE":"E",
    "REFTYPE":"",
    "LANGUFLAG":"",
    "DBPOSITION":0,
    "ANONYMOUS":"",
    "OUTPUTSTYLE":0,
    "SRS_ID":0
   },
   {
    "TABNAME":"ZNWD_SO_HEADER",
    "FIELDNAME":"CLIENT",
    "AS4LOCAL":"N",
    "AS4VERS":0,
    "POSITION":1,
    "KEYFLAG":"X",
    "MANDATORY":"",
    "ROLLNAME":"",
    "CHECKTABLE":"",
    "ADMINFIELD":"0",
    "INTTYPE":"C",
    "INTLEN":6,
    "REFTABLE":"",
    "PRECFIELD":"",
    "REFFIELD":"",
    "CONROUT":"",
    "NOTNULL":"X",
    "DATATYPE":"CLNT",
    "LENG":3,
    "DECIMALS":0,
    "DOMNAME":"",
    "SHLPORIGIN":"",
    "TABLETYPE":"",
    "DEPTH":0,
    "COMPTYPE":"",
    "REFTYPE":"",
    "LANGUFLAG":"",
    "DBPOSITION":0,
    "ANONYMOUS":"",
    "OUTPUTSTYLE":0,
    "SRS_ID":0
   },
   {
    "TABNAME":"ZNWD_SO_HEADER",
    "FIELDNAME":"CREATEDAT",
    "AS4LOCAL":"N",
    "AS4VERS":0,
    "POSITION":15,
    "KEYFLAG":"",
    "MANDATORY":"",
    "ROLLNAME":"TIMESTAMPL",
    "CHECKTABLE":"",
    "ADMINFIELD":"0",
    "INTTYPE":"P",
    "INTLEN":11,
    "REFTABLE":"",
    "PRECFIELD":"",
    "REFFIELD":"",
    "CONROUT":"",
    "NOTNULL":"",
    "DATATYPE":"DEC",
    "LENG":21,
    "DECIMALS":7,
    "DOMNAME":"TZNTSTMPL",
    "SHLPORIGIN":"",
    "TABLETYPE":"",
    "DEPTH":0,
    "COMPTYPE":"E",
    "REFTYPE":"",
    "LANGUFLAG":"",
    "DBPOSITION":0,
    "ANONYMOUS":"",
    "OUTPUTSTYLE":0,
    "SRS_ID":0
   },
   {
    "TABNAME":"ZNWD_SO_HEADER",
    "FIELDNAME":"CREATEDBY",
    "AS4LOCAL":"N",
    "AS4VERS":0,
    "POSITION":14,
    "KEYFLAG":"",
    "MANDATORY":"",
    "ROLLNAME":"SYUNAME",
    "CHECKTABLE":"",
    "ADMINFIELD":"0",
    "INTTYPE":"C",
    "INTLEN":24,
    "REFTABLE":"",
    "PRECFIELD":"",
    "REFFIELD":"",
    "CONROUT":"",
    "NOTNULL":"",
    "DATATYPE":"CHAR",
    "LENG":12,
    "DECIMALS":0,
    "DOMNAME":"SYCHAR12",
    "SHLPORIGIN":"",
    "TABLETYPE":"",
    "DEPTH":0,
    "COMPTYPE":"E",
    "REFTYPE":"",
    "LANGUFLAG":"",
    "DBPOSITION":0,
    "ANONYMOUS":"",
    "OUTPUTSTYLE":0,
    "SRS_ID":0
   },
   {
    "TABNAME":"ZNWD_SO_HEADER",
    "FIELDNAME":"CURRENCYCODE",
    "AS4LOCAL":"N",
    "AS4VERS":0,
    "POSITION":5,
    "KEYFLAG":"",
    "MANDATORY":"",
    "ROLLNAME":"SNWD_CURR_CODE",
    "CHECKTABLE":"",
    "ADMINFIELD":"0",
    "INTTYPE":"C",
    "INTLEN":10,
    "REFTABLE":"",
    "PRECFIELD":"",
    "REFFIELD":"",
    "CONROUT":"",
    "NOTNULL":"",
    "DATATYPE":"CUKY",
    "LENG":5,
    "DECIMALS":0,
    "DOMNAME":"",
    "SHLPORIGIN":"D",
    "TABLETYPE":"",
    "DEPTH":0,
    "COMPTYPE":"E",
    "REFTYPE":"",
    "LANGUFLAG":"",
    "DBPOSITION":0,
    "ANONYMOUS":"",
    "OUTPUTSTYLE":0,
    "SRS_ID":0
   },
   {
    "TABNAME":"ZNWD_SO_HEADER",
    "FIELDNAME":"DELIVERYDATE",
    "AS4LOCAL":"N",
    "AS4VERS":0,
    "POSITION":13,
    "KEYFLAG":"",
    "MANDATORY":"",
    "ROLLNAME":"SNWD_DELIVERY_TIMESTAMPL",
    "CHECKTABLE":"",
    "ADMINFIELD":"0",
    "INTTYPE":"P",
    "INTLEN":11,
    "REFTABLE":"",
    "PRECFIELD":"",
    "REFFIELD":"",
    "CONROUT":"",
    "NOTNULL":"",
    "DATATYPE":"DEC",
    "LENG":21,
    "DECIMALS":7,
    "DOMNAME":"TZNTSTMPL",
    "SHLPORIGIN":"",
    "TABLETYPE":"",
    "DEPTH":0,
    "COMPTYPE":"E",
    "REFTYPE":"",
    "LANGUFLAG":"",
    "DBPOSITION":0,
    "ANONYMOUS":"",
    "OUTPUTSTYLE":0,
    "SRS_ID":0
   },
   {
    "TABNAME":"ZNWD_SO_HEADER",
    "FIELDNAME":"DELIVERYSTATUS",
    "AS4LOCAL":"N",
    "AS4VERS":0,
    "POSITION":10,
    "KEYFLAG":"",
    "MANDATORY":"",
    "ROLLNAME":"SNWD_SO_OR_STATUS_CODE",
    "CHECKTABLE":"",
    "ADMINFIELD":"0",
    "INTTYPE":"C",
    "INTLEN":2,
    "REFTABLE":"",
    "PRECFIELD":"",
    "REFFIELD":"",
    "CONROUT":"",
    "NOTNULL":"",
    "DATATYPE":"CHAR",
    "LENG":1,
    "DECIMALS":0,
    "DOMNAME":"D_SO_OR",
    "SHLPORIGIN":"F",
    "TABLETYPE":"",
    "DEPTH":0,
    "COMPTYPE":"E",
    "REFTYPE":"",
    "LANGUFLAG":"",
    "DBPOSITION":0,
    "ANONYMOUS":"",
    "OUTPUTSTYLE":0,
    "SRS_ID":0
   },
   {
    "TABNAME":"ZNWD_SO_HEADER",
    "FIELDNAME":"GROSSAMOUNT",
    "AS4LOCAL":"N",
    "AS4VERS":0,
    "POSITION":6,
    "KEYFLAG":"",
    "MANDATORY":"",
    "ROLLNAME":"SNWD_TTL_GROSS_AMOUNT",
    "CHECKTABLE":"",
    "ADMINFIELD":"0",
    "INTTYPE":"P",
    "INTLEN":8,
    "REFTABLE":"ZNWD_SO_HEADER",
    "PRECFIELD":"",
    "REFFIELD":"CURRENCYCODE",
    "CONROUT":"",
    "NOTNULL":"",
    "DATATYPE":"CURR",
    "LENG":15,
    "DECIMALS":2,
    "DOMNAME":"",
    "SHLPORIGIN":"",
    "TABLETYPE":"",
    "DEPTH":0,
    "COMPTYPE":"E",
    "REFTYPE":"",
    "LANGUFLAG":"",
    "DBPOSITION":0,
    "ANONYMOUS":"",
    "OUTPUTSTYLE":0,
    "SRS_ID":0
   },
   {
    "TABNAME":"ZNWD_SO_HEADER",
    "FIELDNAME":"LASTCHANGEDAT",
    "AS4LOCAL":"N",
    "AS4VERS":0,
    "POSITION":17,
    "KEYFLAG":"",
    "MANDATORY":"",
    "ROLLNAME":"TIMESTAMPL",
    "CHECKTABLE":"",
    "ADMINFIELD":"0",
    "INTTYPE":"P",
    "INTLEN":11,
    "REFTABLE":"",
    "PRECFIELD":"",
    "REFFIELD":"",
    "CONROUT":"",
    "NOTNULL":"",
    "DATATYPE":"DEC",
    "LENG":21,
    "DECIMALS":7,
    "DOMNAME":"TZNTSTMPL",
    "SHLPORIGIN":"",
    "TABLETYPE":"",
    "DEPTH":0,
    "COMPTYPE":"E",
    "REFTYPE":"",
    "LANGUFLAG":"",
    "DBPOSITION":0,
    "ANONYMOUS":"",
    "OUTPUTSTYLE":0,
    "SRS_ID":0
   },
   {
    "TABNAME":"ZNWD_SO_HEADER",
    "FIELDNAME":"LASTCHANGEDBY",
    "AS4LOCAL":"N",
    "AS4VERS":0,
    "POSITION":16,
    "KEYFLAG":"",
    "MANDATORY":"",
    "ROLLNAME":"SYUNAME",
    "CHECKTABLE":"",
    "ADMINFIELD":"0",
    "INTTYPE":"C",
    "INTLEN":24,
    "REFTABLE":"",
    "PRECFIELD":"",
    "REFFIELD":"",
    "CONROUT":"",
    "NOTNULL":"",
    "DATATYPE":"CHAR",
    "LENG":12,
    "DECIMALS":0,
    "DOMNAME":"SYCHAR12",
    "SHLPORIGIN":"",
    "TABLETYPE":"",
    "DEPTH":0,
    "COMPTYPE":"E",
    "REFTYPE":"",
    "LANGUFLAG":"",
    "DBPOSITION":0,
    "ANONYMOUS":"",
    "OUTPUTSTYLE":0,
    "SRS_ID":0
   },
   {
    "TABNAME":"ZNWD_SO_HEADER",
    "FIELDNAME":"LOCALLASTCHANGEDAT",
    "AS4LOCAL":"N",
    "AS4VERS":0,
    "POSITION":18,
    "KEYFLAG":"",
    "MANDATORY":"",
    "ROLLNAME":"TIMESTAMPL",
    "CHECKTABLE":"",
    "ADMINFIELD":"0",
    "INTTYPE":"P",
    "INTLEN":11,
    "REFTABLE":"",
    "PRECFIELD":"",
    "REFFIELD":"",
    "CONROUT":"",
    "NOTNULL":"",
    "DATATYPE":"DEC",
    "LENG":21,
    "DECIMALS":7,
    "DOMNAME":"TZNTSTMPL",
    "SHLPORIGIN":"",
    "TABLETYPE":"",
    "DEPTH":0,
    "COMPTYPE":"E",
    "REFTYPE":"",
    "LANGUFLAG":"",
    "DBPOSITION":0,
    "ANONYMOUS":"",
    "OUTPUTSTYLE":0,
    "SRS_ID":0
   },
   {
    "TABNAME":"ZNWD_SO_HEADER",
    "FIELDNAME":"NETAMOUNT",
    "AS4LOCAL":"N",
    "AS4VERS":0,
    "POSITION":7,
    "KEYFLAG":"",
    "MANDATORY":"",
    "ROLLNAME":"SNWD_TTL_NET_AMOUNT",
    "CHECKTABLE":"",
    "ADMINFIELD":"0",
    "INTTYPE":"P",
    "INTLEN":8,
    "REFTABLE":"ZNWD_SO_HEADER",
    "PRECFIELD":"",
    "REFFIELD":"CURRENCYCODE",
    "CONROUT":"",
    "NOTNULL":"",
    "DATATYPE":"CURR",
    "LENG":15,
    "DECIMALS":2,
    "DOMNAME":"",
    "SHLPORIGIN":"",
    "TABLETYPE":"",
    "DEPTH":0,
    "COMPTYPE":"E",
    "REFTYPE":"",
    "LANGUFLAG":"",
    "DBPOSITION":0,
    "ANONYMOUS":"",
    "OUTPUTSTYLE":0,
    "SRS_ID":0
   },
   {
    "TABNAME":"ZNWD_SO_HEADER",
    "FIELDNAME":"ORDERUUID",
    "AS4LOCAL":"N",
    "AS4VERS":0,
    "POSITION":2,
    "KEYFLAG":"X",
    "MANDATORY":"",
    "ROLLNAME":"SYSUUID_X16",
    "CHECKTABLE":"",
    "ADMINFIELD":"0",
    "INTTYPE":"X",
    "INTLEN":16,
    "REFTABLE":"",
    "PRECFIELD":"",
    "REFFIELD":"",
    "CONROUT":"",
    "NOTNULL":"X",
    "DATATYPE":"RAW",
    "LENG":16,
    "DECIMALS":0,
    "DOMNAME":"SYSUUID_X16",
    "SHLPORIGIN":"",
    "TABLETYPE":"",
    "DEPTH":0,
    "COMPTYPE":"E",
    "REFTYPE":"",
    "LANGUFLAG":"",
    "DBPOSITION":0,
    "ANONYMOUS":"",
    "OUTPUTSTYLE":0,
    "SRS_ID":0
   },
   {
    "TABNAME":"ZNWD_SO_HEADER",
    "FIELDNAME":"OVERALLSTATUS",
    "AS4LOCAL":"N",
    "AS4VERS":0,
    "POSITION":8,
    "KEYFLAG":"",
    "MANDATORY":"",
    "ROLLNAME":"SNWD_SO_LC_STATUS_CODE",
    "CHECKTABLE":"",
    "ADMINFIELD":"0",
    "INTTYPE":"C",
    "INTLEN":2,
    "REFTABLE":"",
    "PRECFIELD":"",
    "REFFIELD":"",
    "CONROUT":"",
    "NOTNULL":"",
    "DATATYPE":"CHAR",
    "LENG":1,
    "DECIMALS":0,
    "DOMNAME":"D_SO_LC",
    "SHLPORIGIN":"F",
    "TABLETYPE":"",
    "DEPTH":0,
    "COMPTYPE":"E",
    "REFTYPE":"",
    "LANGUFLAG":"",
    "DBPOSITION":0,
    "ANONYMOUS":"",
    "OUTPUTSTYLE":0,
    "SRS_ID":0
   },
   {
    "TABNAME":"ZNWD_SO_HEADER",
    "FIELDNAME":"PAYMENTMETHOD",
    "AS4LOCAL":"N",
    "AS4VERS":0,
    "POSITION":11,
    "KEYFLAG":"",
    "MANDATORY":"",
    "ROLLNAME":"SNWD_SO_PAYMENT_METHOD",
    "CHECKTABLE":"",
    "ADMINFIELD":"0",
    "INTTYPE":"C",
    "INTLEN":2,
    "REFTABLE":"",
    "PRECFIELD":"",
    "REFFIELD":"",
    "CONROUT":"",
    "NOTNULL":"",
    "DATATYPE":"CHAR",
    "LENG":1,
    "DECIMALS":0,
    "DOMNAME":"D_PM",
    "SHLPORIGIN":"F",
    "TABLETYPE":"",
    "DEPTH":0,
    "COMPTYPE":"E",
    "REFTYPE":"",
    "LANGUFLAG":"",
    "DBPOSITION":0,
    "ANONYMOUS":"",
    "OUTPUTSTYLE":0,
    "SRS_ID":0
   },
   {
    "TABNAME":"ZNWD_SO_HEADER",
    "FIELDNAME":"PAYMENTTERMS",
    "AS4LOCAL":"N",
    "AS4VERS":0,
    "POSITION":12,
    "KEYFLAG":"",
    "MANDATORY":"",
    "ROLLNAME":"SNWD_SO_PAYMENT_TERM",
    "CHECKTABLE":"",
    "ADMINFIELD":"0",
    "INTTYPE":"C",
    "INTLEN":2,
    "REFTABLE":"",
    "PRECFIELD":"",
    "REFFIELD":"",
    "CONROUT":"",
    "NOTNULL":"",
    "DATATYPE":"CHAR",
    "LENG":1,
    "DECIMALS":0,
    "DOMNAME":"D_PT",
    "SHLPORIGIN":"F",
    "TABLETYPE":"",
    "DEPTH":0,
    "COMPTYPE":"E",
    "REFTYPE":"",
    "LANGUFLAG":"",
    "DBPOSITION":0,
    "ANONYMOUS":"",
    "OUTPUTSTYLE":0,
    "SRS_ID":0
   },
   {
    "TABNAME":"ZNWD_SO_HEADER",
    "FIELDNAME":"SALESORDERID",
    "AS4LOCAL":"N",
    "AS4VERS":0,
    "POSITION":3,
    "KEYFLAG":"",
    "MANDATORY":"",
    "ROLLNAME":"SNWD_SO_ID",
    "CHECKTABLE":"",
    "ADMINFIELD":"0",
    "INTTYPE":"C",
    "INTLEN":20,
    "REFTABLE":"",
    "PRECFIELD":"",
    "REFFIELD":"",
    "CONROUT":"",
    "NOTNULL":"",
    "DATATYPE":"CHAR",
    "LENG":10,
    "DECIMALS":0,
    "DOMNAME":"D_EPM_ID",
    "SHLPORIGIN":"",
    "TABLETYPE":"",
    "DEPTH":0,
    "COMPTYPE":"E",
    "REFTYPE":"",
    "LANGUFLAG":"",
    "DBPOSITION":0,
    "ANONYMOUS":"",
    "OUTPUTSTYLE":0,
    "SRS_ID":0
   }
  ]
 },
 {
  "table":"DD03T",
  "data":
  [
   {
    "TABNAME":"ZNWD_SO_HEADER",
    "DDLANGUAGE":"E",
    "AS4LOCAL":"N",
    "FIELDNAME":"CLIENT",
    "DDTEXT":""
   }
  ]
 },
 {
  "table":"DD09L",
  "data":
  [
   {
    "TABNAME":"ZNWD_SO_HEADER",
    "AS4LOCAL":"N",
    "AS4VERS":0,
    "TABKAT":"0",
    "TABART":"APPL0",
    "PUFFERUNG":"",
    "SCHFELDANZ":0,
    "PROTOKOLL":"",
    "SPEICHPUFF":"",
    "AS4USER":"DEVELOPER",
    "AS4DATE":"0000-00-00",
    "AS4TIME":"00:00:00",
    "TRANSPFLAG":"",
    "RESERVE":"",
    "UEBERSETZ":"",
    "ACTFLAG":"",
    "BUFALLOW":"N",
    "JAVAONLY":"",
    "ROWORCOLST":"C",
    "SHARINGTYPE":"",
    "LOAD_UNIT":""
   }
  ]
 },
 {
  "table":"DD12L",
  "data":
  [
   {
    "SQLTAB":"ZNWD_SO_HEADER",
    "INDEXNAME":"001",
    "AS4LOCAL":"L",
    "AS4VERS":0,
    "AUTHCLASS":0,
    "UNIQUEFLAG":"",
    "AS4USER":"DEVELOPER",
    "AS4DATE":"0000-00-00",
    "AS4TIME":"00:00:00",
    "ACTFLAG":"",
    "DBINDEX":"",
    "DBSTATE":"",
    "DBINCLEXCL":"",
    "DBSYSSEL1":"",
    "DBSYSSEL2":"",
    "DBSYSSEL3":"",
    "DBSYSSEL4":"",
    "ISEXTIND":"",
    "FULL_TEXT":"",
    "LANGU_COLUMN":"",
    "MIME_TYPE_COL":"",
    "MIME_TYPE":"",
    "LANGU_DETECTION":"",
    "FAST_PREPROCESS":"",
    "FUZZY_SEARCH_INDX":"",
    "SEARCH_ONLY":"",
    "UPDATE_MODE":"",
    "CONFIGURATION":"",
    "PHRASE_INDX_RATIO":0,
    "TEXT_ANALYSIS":"",
    "TOKEN_SEPARATORS":""
   }
  ]
 },
 {
  "table":"DD12T",
  "data":
  [
   {
    "DDLANGUAGE":"E",
    "SQLTAB":"ZNWD_SO_HEADER",
    "INDEXNAME":"001",
    "AS4LOCAL":"N",
    "AS4VERS":0,
    "DDTEXT":"TEst index"
   }
  ]
 },
 {
  "table":"DD17S",
  "data":
  [
   {
    "SQLTAB":"ZNWD_SO_HEADER",
    "INDEXNAME":"001",
    "POSITION":1,
    "AS4LOCAL":"N",
    "AS4VERS":0,
    "FIELDNAME":"ORDERUUID",
    "DESCFLAG":""
   },
   {
    "SQLTAB":"ZNWD_SO_HEADER",
    "INDEXNAME":"001",
    "POSITION":2,
    "AS4LOCAL":"N",
    "AS4VERS":0,
    "FIELDNAME":"SALESORDERID",
    "DESCFLAG":""
   }
  ]
 },
 {
  "table":"DDTYPES",
  "data":
  [
   {
    "TYPENAME":"ZNWD_SO_HEADER",
    "STATE":"N",
    "TYPEKIND":"TABL"
   }
  ]
 },
 {
  "table":"TADIR",
  "data":
  [
   {
    "PGMID":"R3TR",
    "OBJECT":"TABL",
    "OBJ_NAME":"ZNWD_SO_HEADER",
    "KORRNUM":"",
    "SRCSYSTEM":"...",
    "AUTHOR":"DEVELOPER",
    "SRCDEP":"",
    "DEVCLASS":"ZM_RAP_SOM",
    "GENFLAG":"",
    "EDTFLAG":"",
    "CPROJECT":" S",
    "MASTERLANG":"E",
    "VERSID":"",
    "PAKNOCHECK":"",
    "OBJSTABLTY":"",
    "COMPONENT":"",
    "CRELEASE":"",
    "DELFLAG":"",
    "TRANSLTTXT":"",
    "CREATED_ON":"2024-04-30",
    "CHECK_DATE":"2024-04-30",
    "CHECK_CFG":""
   }
  ]
 }
]